xontrib/xgit/__init__.py
xontrib/xgit/cmds/__init__.py
xontrib/xgit/cmds/cd.py
xontrib/xgit/cmds/ls.py
xontrib/xgit/cmds/pwd.py
xontrib/xgit/context.py
xontrib/xgit/context_types.py
xontrib/xgit/conversion_mgr.py
xontrib/xgit/decorators.py
xontrib/xgit/display.py
xontrib/xgit/entries.py
xontrib/xgit/entry_types.py
xontrib/xgit/git_cmd.py
xontrib/xgit/git_path.py
xontrib/xgit/identity_set.py
xontrib/xgit/ids.py
xontrib/xgit/invoker.py
xontrib/xgit/main.py
xontrib/xgit/object_types.py
xontrib/xgit/objects.py
xontrib/xgit/person.py
xontrib/xgit/ref.py
xontrib/xgit/ref_types.py
xontrib/xgit/repository.py
xontrib/xgit/runners.py
xontrib/xgit/type_aliases.py
xontrib/xgit/type_aliases_310.py
xontrib/xgit/types.py
xontrib/xgit/utils.py
xontrib/xgit/views/__init__.py
xontrib/xgit/views/json_types.py
xontrib/xgit/views/multiview.py
xontrib/xgit/views/table.py
xontrib/xgit/views/to_json.py
xontrib/xgit/views/view.py
xontrib/xgit/worktree.py
xontrib_xgit-0.0.7.dist-info/LICENSE
xontrib_xgit-0.0.7.dist-info/METADATA
xontrib_xgit-0.0.7.dist-info/WHEEL
xontrib_xgit-0.0.7.dist-info/RECORD
