Metadata-Version: 2.1
Name: xontrib-xgit
Version: 0.0.7
Summary: Git exploration utilities for xonsh.
Home-page: https://github.com/BobKerns/xontrib-xgit
License: MIT
Keywords: xontrib,xonsh,git
Author: Bob Kerns
Author-email: 1154903+BobKerns@users.noreply.github.com
Requires-Python: >=3.10,<4.0
Classifier: Intended Audience :: Developers
Classifier: License :: OSI Approved :: MIT License
Classifier: Natural Language :: English
Classifier: Operating System :: OS Independent
Classifier: Programming Language :: Python :: 3
Classifier: Programming Language :: Python :: 3.10
Classifier: Programming Language :: Python :: 3.11
Classifier: Programming Language :: Python :: 3.12
Classifier: Programming Language :: Python :: 3.13
Classifier: Topic :: Software Development :: Version Control :: Git
Classifier: Topic :: System :: Shells
Classifier: Topic :: System :: System Shells
Classifier: Topic :: Terminals
Requires-Dist: colorama (>=0.4.6)
Requires-Dist: ipython (>=8.30.0)
Requires-Dist: prompt_toolkit (>=3.0.48)
Requires-Dist: pyreadline3 (>=3.5.4)
Requires-Dist: pyyaml (>=6.0.2)
Requires-Dist: xonsh (>=0.19.0)
Project-URL: Code, https://github.com/BobKerns/xontrib-xgit
Project-URL: Documentation, https://github.com/BobKerns/xontrib-xgit/blob/master/README.md
Project-URL: Issue tracker, https://github.com/BobKerns/xontrib-xgit/issues
Project-URL: Repository, https://github.com/BobKerns/xontrib-xgit
